Metadata-Version: 2.1
Name: latex_generator_hw2
Version: 0.3.2
Summary: A simple Python package
Author: shamank
Author-email: russyakrusya@gmail.com
Classifier: Programming Language :: Python :: 3
Classifier: License :: OSI Approved :: MIT License
Classifier: Operating System :: OS Independent
Requires-Python: >=3.10
License-File: LICENSE.txt
